probador.v
module probador(
    output reg clk,
    output reg reset_L,
    output reg [3:0] dataA, dataB,
    input [3:0] sum30_dd, idx_dd
);



initial begin
	$dumpfile("sumador.vcd");
	$dumpvars;

    {reset_L} = 1'b0;
    @(posedge clk);	
    {reset_L} = 1'b1;
    {dataA} = 4'b0000;
    {dataB} = 4'b1111;
    repeat (7) begin

            // Espera/sincroniza con el flanco positivo del reloj	
            @(posedge clk);	
            {dataA} <= {dataA} +1 ;
            {dataB} <= {dataB} +1;
            {reset_L} = 1'b1;
    end

	$finish;
end  
   


    //Valor inicial del reloj para que no sea indeterminado
	initial	clk 	<= 0;	

    //Toggle cada 2*10 nano segundos		
	always	#1 clk 	<= ~clk;

endmodule

sum_pipe.v
module sum_pipe(
    input clk, reset_L,
    input [3:0] dataA, dataB,
    output reg [3:0] sum30_dd, idx_dd
);

    reg [1:0] acarreo, acarreo_d;
    reg [2:0] sum_conacarreo;
    reg [3:0] sum30_d, dataA_d, dataB_d, dataAant, dataBant, idx,idx_d;
    reg [1:0] sum10, sum10_d;

    always @(*) begin
        if (reset_L) begin
            sum_conacarreo <= dataA[1:0] + dataB[1:0];
            sum10 <= sum_conacarreo[1:0];
            acarreo <= sum_conacarreo[2];
            dataAant  = dataA;
            dataBant = dataB;
            
        end
        else begin
            sum_conacarreo = 0;
            sum10 = 0;
            acarreo = 0;
            sum10_d = 0;
            acarreo_d = 0;
            sum30_d = 0;
            dataAant  = 0;
            dataBant = 0;
            idx = 0;
        end


    end
   //Segundo Etapa ya va tener 2 tiempos de retraso
   always @(posedge clk) begin
       idx <= idx +1;
       idx_d <= idx;
       idx_dd <= idx_d;
       sum10_d <= sum10;
       acarreo_d <= acarreo;
       sum30_d[3:2] <= dataAant[3:2] + dataBant[3:2]+ acarreo;
       sum30_dd[3:2] <= dataA_d[3:2] + dataB_d[3:2]+ acarreo_d;
       dataA_d<= dataAant;
       dataB_d <= dataBant;   
       sum30_d[1:0] <= sum10;
       sum30_dd[1:0] <= sum10_d;
   end 
 
endmodule

sumador.v
`include "sum_pipe.v"

module sumador(
    input clk,reset_L,
    input [3:0] dataA, dataB,
    output [3:0] sum30_dd, idx_dd
);

    sum_pipe sum(.reset_L(reset_L), .clk(clk), .dataA(dataA), .dataB(dataB), .sum30_dd(sum30_dd), .idx_dd(idx_dd));
    

endmodule

bancosumador.v
//++++++++++BANCO PRUEBAS +++++++++++++++


`timescale 	1ns	/ 100ps

`include "sumador.v"
`include "probador.v"

 // Testbench

module bancopruebas_sumador;

    /*AUTOWIRE*/
    // Beginning of automatic wires (for undeclared instantiated-module outputs)
    wire		clk;			// From probador_sumador of probador.v
    wire [3:0]		dataA;			// From probador_sumador of probador.v
    wire [3:0]		dataB;			// From probador_sumador of probador.v
    wire [3:0]		idx_dd;			// From sum of sumador.v
    wire		reset_L;		// From probador_sumador of probador.v
    wire [3:0]		sum30_dd;		// From sum of sumador.v
    // End of automatics
    

	sumador sum(/*AUTOINST*/
		    // Outputs
		    .sum30_dd		(sum30_dd[3:0]),
		    .idx_dd		(idx_dd[3:0]),
		    // Inputs
		    .clk		(clk),
		    .reset_L		(reset_L),
		    .dataA		(dataA[3:0]),
		    .dataB		(dataB[3:0]));
	probador probador_sumador(/*AUTOINST*/
				  // Outputs
				  .clk			(clk),
				  .reset_L		(reset_L),
				  .dataA		(dataA[3:0]),
				  .dataB		(dataB[3:0]),
				  // Inputs
				  .sum30_dd		(sum30_dd[3:0]),
				  .idx_dd		(idx_dd[3:0]));
	

endmodule

sumador.vcd
$date
	Wed Jul  7 21:20:59 2021
$end
$version
	Icarus Verilog
$end
$timescale
	100ps
$end
$scope module bancopruebas_sumador $end
$var wire 4 ! sum30_dd [3:0] $end
$var wire 1 " reset_L $end
$var wire 4 # idx_dd [3:0] $end
$var wire 4 $ dataB [3:0] $end
$var wire 4 % dataA [3:0] $end
$var wire 1 & clk $end
$scope module probador_sumador $end
$var wire 4 ' sum30_dd [3:0] $end
$var wire 4 ( idx_dd [3:0] $end
$var reg 1 & clk $end
$var reg 4 ) dataA [3:0] $end
$var reg 4 * dataB [3:0] $end
$var reg 1 " reset_L $end
$upscope $end
$scope module sum $end
$var wire 1 & clk $end
$var wire 4 + dataA [3:0] $end
$var wire 4 , dataB [3:0] $end
$var wire 1 " reset_L $end
$var wire 4 - sum30_dd [3:0] $end
$var wire 4 . idx_dd [3:0] $end
$scope module sum $end
$var wire 1 & clk $end
$var wire 4 / dataA [3:0] $end
$var wire 4 0 dataB [3:0] $end
$var wire 1 " reset_L $end
$var reg 2 1 acarreo [1:0] $end
$var reg 2 2 acarreo_d [1:0] $end
$var reg 4 3 dataA_d [3:0] $end
$var reg 4 4 dataAant [3:0] $end
$var reg 4 5 dataB_d [3:0] $end
$var reg 4 6 dataBant [3:0] $end
$var reg 4 7 idx [3:0] $end
$var reg 4 8 idx_d [3:0] $end
$var reg 4 9 idx_dd [3:0] $end
$var reg 2 : sum10 [1:0] $end
$var reg 2 ; sum10_d [1:0] $end
$var reg 4 < sum30_d [3:0] $end
$var reg 4 = sum30_dd [3:0] $end
$var reg 3 > sum_conacarreo [2:0] $end
$upscope $end
$upscope $end
$upscope $end
$enddefinitions $end
#0
$dumpvars
b0 >
bx =
b0 <
b0 ;
b0 :
bx 9
bx 8
b0 7
b0 6
bx 5
b0 4
bx 3
b0 2
b0 1
bx 0
bx /
bx .
bx -
bx ,
bx +
bx *
bx )
bx (
bx '
0&
bx %
bx $
bx #
0"
bx !
$end
#10
b11 :
b11 >
bx00 !
bx00 '
bx00 -
bx00 =
b0 5
b0 3
b0 8
b1 7
b1111 6
b1111 $
b1111 *
b1111 ,
b1111 0
b0 %
b0 )
b0 +
b0 /
1"
1&
#20
0&
#30
b1 :
b1 >
b0 6
b1 4
b0 $
b0 *
b0 ,
b0 0
b1 %
b1 )
b1 +
b1 /
b1111 5
b0 !
b0 '
b0 -
b0 =
b1111 <
b11 ;
b0 #
b0 (
b0 .
b0 9
b1 8
b10 7
1&
#40
0&
#50
b11 :
b11 >
b1 6
b10 4
b0 5
b1 3
b1111 !
b1111 '
b1111 -
b1111 =
b1 <
b1 ;
b1 #
b1 (
b1 .
b1 9
b10 8
b11 7
b1 $
b1 *
b1 ,
b1 0
b10 %
b10 )
b10 +
b10 /
1&
#60
0&
#70
b1 1
b1 :
b101 >
b10 6
b11 4
b10 $
b10 *
b10 ,
b10 0
b11 %
b11 )
b11 +
b11 /
b11 <
b1 5
b10 3
b1 !
b1 '
b1 -
b1 =
b11 ;
b10 #
b10 (
b10 .
b10 9
b11 8
b100 7
1&
#80
0&
#90
b0 1
b11 :
b11 >
b11 6
b100 4
b11 !
b11 '
b11 -
b11 =
b10 5
b11 3
b101 <
b1 2
b1 ;
b11 #
b11 (
b11 .
b11 9
b100 8
b101 7
b11 $
b11 *
b11 ,
b11 0
b100 %
b100 )
b100 +
b100 /
1&
#100
0&
#110
b1 :
b1 >
b100 6
b101 4
b100 $
b100 *
b100 ,
b100 0
b101 %
b101 )
b101 +
b101 /
b111 <
b11 5
b100 3
b101 !
b101 '
b101 -
b101 =
b0 2
b11 ;
b100 #
b100 (
b100 .
b100 9
b101 8
b110 7
1&
#120
0&
#130
b11 :
b11 >
b101 6
b110 4
b111 !
b111 '
b111 -
b111 =
b100 5
b101 3
b1001 <
b1 ;
b101 #
b101 (
b101 .
b101 9
b110 8
b111 7
b101 $
b101 *
b101 ,
b101 0
b110 %
b110 )
b110 +
b110 /
1&
#140
0&
#150
b1 1
b1 :
b101 >
b110 6
b111 4
b110 $
b110 *
b110 ,
b110 0
b111 %
b111 )
b111 +
b111 /
b1011 <
b101 5
b110 3
b1001 !
b1001 '
b1001 -
b1001 =
b11 ;
b110 #
b110 (
b110 .
b110 9
b111 8
b1000 7
1&
